tracksegnet/__init__.py
tracksegnet/analysis.py
tracksegnet/compute_features.py
tracksegnet/experimental_tracks.py
tracksegnet/generate_lstm_model.py
tracksegnet/simulate_tracks.py
tracksegnet/utils.py
tracksegnet-1.2.5.dist-info/METADATA
tracksegnet-1.2.5.dist-info/WHEEL
tracksegnet-1.2.5.dist-info/licenses/LICENSE
tracksegnet-1.2.5.dist-info/RECORD
