Metadata-Version: 2.1
Name: tracksegnet
Version: 1.2.5
Summary: Segmentation of trajectories into diffusive states using supervised LSTM network
Project-URL: Homepage, https://github.com/hkabbech/TrackSegNet
Project-URL: Issues, https://github.com/hkabbech/TrackSegNet/issues
Author-email: Hélène Kabbech <helene.kabbech@gmail.com>
License-File: LICENSE
Classifier: License :: OSI Approved :: MIT License
Classifier: Operating System :: OS Independent
Classifier: Programming Language :: Python :: 3
Requires-Python: >=3.8
Requires-Dist: absl-py==1.4.0
Requires-Dist: astunparse==1.6.3
Requires-Dist: cachetools==5.3.0
Requires-Dist: certifi>=2023.7.22
Requires-Dist: charset-normalizer==3.0.1
Requires-Dist: contourpy==1.0.7
Requires-Dist: cycler==0.11.0
Requires-Dist: flatbuffers==23.1.21
Requires-Dist: fonttools==4.43.0
Requires-Dist: gast==0.4.0
Requires-Dist: google-auth-oauthlib==0.4.6
Requires-Dist: google-auth==2.16.0
Requires-Dist: google-pasta==0.2.0
Requires-Dist: grpcio>=1.53.0
Requires-Dist: h5py==3.8.0
Requires-Dist: idna==3.4
Requires-Dist: importlib-metadata==6.0.0
Requires-Dist: keras==2.11.0
Requires-Dist: kiwisolver==1.4.4
Requires-Dist: libclang==15.0.6.1
Requires-Dist: markdown==3.4.1
Requires-Dist: markupsafe==2.1.2
Requires-Dist: matplotlib==3.6.3
Requires-Dist: more-itertools==9.0.0
Requires-Dist: myst-parser>=2.0.0
Requires-Dist: numpy==1.24.1
Requires-Dist: oauthlib==3.2.2
Requires-Dist: opt-einsum==3.3.0
Requires-Dist: packaging==23.0
Requires-Dist: pandas==1.5.3
Requires-Dist: pillow>=10.0.1
Requires-Dist: protobuf==3.19.6
Requires-Dist: pyasn1-modules==0.2.8
Requires-Dist: pyasn1==0.4.8
Requires-Dist: pyparsing==3.0.9
Requires-Dist: python-dateutil==2.8.2
Requires-Dist: pytz==2022.7.1
Requires-Dist: readthedocs-sphinx-search>=0.1.1
Requires-Dist: requests-oauthlib==1.3.1
Requires-Dist: requests>=2.31.0
Requires-Dist: rsa==4.9
Requires-Dist: scipy==1.10.0
Requires-Dist: seaborn==0.12.2
Requires-Dist: six==1.16.0
Requires-Dist: sphinx-rtd-theme>=2.0.0
Requires-Dist: sphinx>=7.0.0
Requires-Dist: tensorboard-data-server==0.6.1
Requires-Dist: tensorboard-plugin-wit==1.8.1
Requires-Dist: tensorboard==2.11.2
Requires-Dist: tensorflow-estimator==2.11.0
Requires-Dist: tensorflow-io-gcs-filesystem==0.30.0
Requires-Dist: tensorflow==2.11.1
Requires-Dist: termcolor==2.2.0
Requires-Dist: tqdm==4.64.1
Requires-Dist: typing-extensions==4.4.0
Requires-Dist: urllib3>=1.26.18
Requires-Dist: werkzeug>=2.3.8
Requires-Dist: wrapt==1.14.1
Requires-Dist: zipp==3.11.0
